matrix_operations_zjh/__init__.py
matrix_operations_zjh/operations.py
matrix_operations_zjh-1.0.0.dist-info/LICENSE
matrix_operations_zjh-1.0.0.dist-info/METADATA
matrix_operations_zjh-1.0.0.dist-info/WHEEL
matrix_operations_zjh-1.0.0.dist-info/entry_points.txt
matrix_operations_zjh-1.0.0.dist-info/top_level.txt
matrix_operations_zjh-1.0.0.dist-info/RECORD
