Metadata-Version: 2.1
Name: matrix_operations_zjh
Version: 1.0.0
Summary: A simple package for matrix operations
Home-page: http://www.example.com
Author: zjh
Author-email: 3398727636@qq.com
Classifier: Programming Language :: Python :: 3
Classifier: License :: OSI Approved :: MIT License
Classifier: Operating System :: OS Independent
Requires-Python: >=3.6
License-File: LICENSE
Provides-Extra: dev
Requires-Dist: check-manifest; extra == "dev"
Provides-Extra: test
Requires-Dist: coverage; extra == "test"
